LICENSE
MANIFEST.in
README.rst
setup.py
django_standard_form.egg-info/PKG-INFO
django_standard_form.egg-info/SOURCES.txt
django_standard_form.egg-info/dependency_links.txt
django_standard_form.egg-info/not-zip-safe
django_standard_form.egg-info/requires.txt
django_standard_form.egg-info/top_level.txt
standard_form/__init__.py
standard_form/models.py
standard_form/templates/standard_form/field.html
standard_form/templates/standard_form/form.html
standard_form/templates/standard_form/non_field_errors.html
standard_form/templates/standard_form/submit.html
standard_form/templatetags/__init__.py
standard_form/templatetags/__init__.pyc
standard_form/templatetags/standard_form.py
standard_form/templatetags/standard_form.pyc